[{"original_text": "把委屈和泪水都咽下去，输不起就不要输，死不了就站起来，告诉所有看不起你的人：我很好。", "username": "解放先生", "province": 100, "statuses_count": 6770, "friends_count": 13, "city": 1000, "text": "把委屈和泪水都咽下去，输不起就不要输，死不了就站起来，告诉所有看不起你的人：我很好。", "user_description": "呈现一个时代的真相", "mid": "3919861736900828", "verified_reason": "", "followers_count": 111226, "parent": "", "t": 1450051328, "gender": "m", "verified": false, "verified_type": -1, "uid": "2639018411"}, {"original_text": "哪那么多人看你，更不谈看不看得起。", "username": "狐狸哥哥_", "province": 42, "statuses_count": 822, "friends_count": 138, "city": 1000, "text": "哪那么多人看你，更不谈看不看得起。", "user_description": "勿忘初心，不违初衷，慎始如終。", "mid": "3919862193887802", "verified_reason": "", "followers_count": 3901, "parent": "3919861736900828", "t": 1450051437, "gender": "m", "verified": false, "verified_type": -1, "uid": "1497187471"}, {"original_text": "轉發微博", "username": "梁宝宝我爱你_hp", "province": 22, "statuses_count": 1824, "friends_count": 237, "city": 1, "text": "轉發微博", "user_description": "没有等待，怎么会有未来。", "mid": "3919863196018202", "verified_reason": "", "followers_count": 11, "parent": "3919861736900828", "t": 1450051675, "gender": "m", "verified": false, "verified_type": -1, "uid": "2484015335"}, {"original_text": "转发微博", "username": "张智_sky", "province": 37, "statuses_count": 4200, "friends_count": 370, "city": 1, "text": "转发微博", "user_description": "洗洗睡吧", "mid": "3919863665414828", "verified_reason": "", "followers_count": 86, "parent": "3919861736900828", "t": 1450051788, "gender": "m", "verified": false, "verified_type": -1, "uid": "1197999711"}, {"original_text": "转发微博", "username": "柠檬味小姑娘", "province": 37, "statuses_count": 728, "friends_count": 796, "city": 1, "text": "转发微博", "user_description": "稳住局面 沉住气", "mid": "3919865364518080", "verified_reason": "", "followers_count": 125, "parent": "3919861736900828", "t": 1450052193, "gender": "f", "verified": false, "verified_type": -1, "uid": "5287282684"}, {"original_text": "转发微博", "username": "男神有妇男症", "province": 400, "statuses_count": 3627, "friends_count": 296, "city": 3, "text": "转发微博", "user_description": "可以滚了", "mid": "3919882418940235", "verified_reason": "", "followers_count": 106, "parent": "3919861736900828", "t": 1450056259, "gender": "f", "verified": false, "verified_type": -1, "uid": "5166217608"}, {"original_text": "转发微博", "username": "用户5684723938", "province": 100, "statuses_count": 94, "friends_count": 60, "city": 1000, "text": "转发微博", "user_description": "", "mid": "3919883895169683", "verified_reason": "", "followers_count": 1, "parent": "3919861736900828", "t": 1450056611, "gender": "m", "verified": false, "verified_type": -1, "uid": "5684723938"}, {"original_text": "转发微博", "username": "聪聪小文", "province": 100, "statuses_count": 916, "friends_count": 374, "city": 1000, "text": "转发微博", "user_description": "简单单纯傻大妞，乐活人生", "mid": "3919886562826116", "verified_reason": "", "followers_count": 83, "parent": "3919861736900828", "t": 1450057246, "gender": "f", "verified": false, "verified_type": -1, "uid": "3835720311"}, {"original_text": "转发微博", "username": "娜娜童鞋V5", "province": 33, "statuses_count": 1320, "friends_count": 236, "city": 3, "text": "转发微博", "user_description": "", "mid": "3919896260299030", "verified_reason": "", "followers_count": 79, "parent": "3919861736900828", "t": 1450059559, "gender": "f", "verified": false, "verified_type": -1, "uid": "2718547233"}, {"original_text": "转发微博", "username": "墙角的蔷薇花2014520", "province": 34, "statuses_count": 683, "friends_count": 212, "city": 1, "text": "转发微博", "user_description": "爱我所爱，选我所选…………", "mid": "3919900580211356", "verified_reason": "", "followers_count": 10, "parent": "3919861736900828", "t": 1450060589, "gender": "f", "verified": false, "verified_type": -1, "uid": "5679005528"}, {"original_text": "转发微博", "username": "巧克力27的s蓝调", "province": 100, "statuses_count": 4435, "friends_count": 258, "city": 1000, "text": "转发微博", "user_description": "", "mid": "3919918653215111", "verified_reason": "", "followers_count": 517, "parent": "3919861736900828", "t": 1450064898, "gender": "f", "verified": false, "verified_type": -1, "uid": "1011756672"}, {"original_text": "转发微博", "username": "任丽梅meizi", "province": 61, "statuses_count": 158, "friends_count": 260, "city": 8, "text": "转发微博", "user_description": "自己是梧桐，凤凰才会来栖；自己是大海，百川才来汇聚。", "mid": "3920076148921150", "verified_reason": "", "followers_count": 136, "parent": "3919861736900828", "t": 1450102448, "gender": "f", "verified": false, "verified_type": -1, "uid": "3176461717"}]