[{"original_text": "回复@阿郎的心声1966:好多二悲流氓都认同社会主义，他们不过是举着社会主义的旗子，企图掩盖自己不劳而获的龌龊心理。//@阿郎的心声1966:孔老师应该耐心点，这人虽笨，但好像也认同社会主义。//@孔庆东:回复@失忆-會過去的:你确实失忆了，因为不大愿意相信你也是二悲。", "username": "孔庆东", "province": 11, "statuses_count": 61884, "friends_count": 570, "city": 8, "text": "回复@阿郎的心声1966:好多二悲流氓都认同社会主义，他们不过是举着社会主义的旗子，企图掩盖自己不劳而获的龌龊心理。", "user_description": "联系讲座、会议、约稿、访谈、剪彩、顾问、嘉宾、策划、取名、占卜等严肃事项者，勿与本人联系，敬请发函至zhugebiyao@sina.com与魏先生联系。", "mid": "3926951658001375", "verified_reason": "北京大学中文系教授孔庆东", "followers_count": 2856173, "parent": "", "t": 1451741697, "gender": "m", "verified": true, "verified_type": 0, "uid": "1198367585"}, {"original_text": "//@孔庆东:回复@阿郎的心声1966:好多二悲流氓都认同社会主义，他们不过是举着社会主义的旗子，企图掩盖自己不劳而获的龌龊心理。//@阿郎的心声1966:孔老师应该耐心点，这人虽笨，但好像也认同社会主义。//@孔庆东:回复@失忆-會過去的:你确实失忆了，因为不大愿意相信你也是二悲。", "username": "健坤强德之声闻", "province": 36, "statuses_count": 40085, "friends_count": 876, "city": 1000, "text": "", "user_description": "“健坤强德”微博于去年被腥狼残忍莫名而注销之，而博客之名亦被篡改为‘健坤强德_bZg’，只能阅读和转载，隐忍一年余，搬家到此，开始博客新生！", "mid": "3926953272693814", "verified_reason": "", "followers_count": 774, "parent": "3926951658001375", "t": 1451742081, "gender": "m", "verified": false, "verified_type": -1, "uid": "3958344200"}, {"original_text": "//@孔庆东: 回复@阿郎的心声1966:好多二悲流氓都认同社会主义，他们不过是举着社会主义的旗子，企图掩盖自己不劳而获的龌龊心理。//@阿郎的心声1966:孔老师应该耐心点，这人虽笨，但好像也认同社会主义。//@孔庆东:回复@失忆-會過去的:你确实失忆了，因为不大愿意相信你也是二悲。", "username": "入梦化蝶丶", "province": 37, "statuses_count": 5270, "friends_count": 70, "city": 1, "text": "", "user_description": "未来的土鳖党员", "mid": "3926953880556292", "verified_reason": "", "followers_count": 123, "parent": "3926951658001375", "t": 1451742227, "gender": "m", "verified": false, "verified_type": -1, "uid": "5283370041"}, {"original_text": "回头写一篇《左派要注重枪杆子（金钱）》//@孔庆东:回复@阿郎的心声1966:好多二悲流氓都认同社会主义，他们不过是举着社会主义的旗子，企图掩盖自己不劳而获的龌龊心理。//@阿郎的心声1966:孔老师应该耐心点，这人虽笨，但好像也认同社会主义。//@孔庆东:回复@失忆-會過去的:你确实失忆了，因为不大", "username": "智仁书院", "province": 42, "statuses_count": 1533, "friends_count": 495, "city": 1, "text": "回头写一篇《左派要注重枪杆子（金钱）》", "user_description": "教育塑造性格，学习改善命运！", "mid": "3926960851691982", "verified_reason": "", "followers_count": 1430, "parent": "3926951658001375", "t": 1451743888, "gender": "m", "verified": false, "verified_type": 220, "uid": "2300151724"}, {"original_text": "说得太好啦，孔老师！ //@孔庆东:回复@阿郎的心声1966:好多二悲流氓都认同社会主义，他们不过是举着社会主义的旗子，企图掩盖自己不劳而获的龌龊心理。//@阿郎的心声1966:孔老师应该耐心点，这人虽笨，但好像也认同社会主义。//@孔庆东:回复@失忆-會過去的:你确实失忆了，因为不大愿意相信你也是二悲。", "username": "我就要转弯", "province": 32, "statuses_count": 2472, "friends_count": 574, "city": 1, "text": "说得太好啦，孔老师！ ", "user_description": "中共澎湖地委书记", "mid": "3926965579030620", "verified_reason": "", "followers_count": 311, "parent": "3926951658001375", "t": 1451745016, "gender": "m", "verified": false, "verified_type": -1, "uid": "1902021671"}, {"original_text": "//@孔庆东:回复@阿郎的心声1966:好多二悲流氓都认同社会主义，他们不过是举着社会主义的旗子，企图掩盖自己不劳而获的龌龊心理。//@阿郎的心声1966:孔老师应该耐心点，这人虽笨，但好像也认同社会主义。//@孔庆东:回复@失忆-會過去的:你确实失忆了，因为不大愿意相信你也是二悲。", "username": "寒塘剑影", "province": 42, "statuses_count": 26067, "friends_count": 1257, "city": 1000, "text": "", "user_description": "以孔庆东老师为榜样，做坚定的人民派。", "mid": "3926970280245663", "verified_reason": "", "followers_count": 408, "parent": "3926951658001375", "t": 1451746136, "gender": "m", "verified": false, "verified_type": 220, "uid": "2881669304"}, {"original_text": "还有人相信马克思的社会论//@孔庆东:回复@阿郎的心声1966:好多二悲流氓都认同社会主义，他们不过是举着社会主义的旗子，企图掩盖自己不劳而获的龌龊心理。//@阿郎的心声1966:孔老师应该耐心点，这人虽笨，但好像也认同社会主义。", "username": "古城逸风1", "province": 51, "statuses_count": 5599, "friends_count": 1904, "city": 1, "text": "还有人相信马克思的社会论", "user_description": "中国微法庭首席法官一做有种中国人不做亡国奴，宁可站着死绝不跪着生!", "mid": "3926982406812447", "verified_reason": "", "followers_count": 1630, "parent": "3926951658001375", "t": 1451749027, "gender": "m", "verified": false, "verified_type": -1, "uid": "1220197463"}, {"original_text": "//@孔庆东:回复@阿郎的心声1966:好多二悲流氓都认同社会主义，他们不过是举着社会主义的旗子，企图掩盖自己不劳而获的龌龊心理。//@阿郎的心声1966:孔老师应该耐心点，这人虽笨，但好像也认同社会主义。//@孔庆东:回复@失忆-會過去的:你确实失忆了，因为不大愿意相信你也是二悲。", "username": "新黔星火", "province": 52, "statuses_count": 10679, "friends_count": 135, "city": 1, "text": "", "user_description": "", "mid": "3926988245080111", "verified_reason": "", "followers_count": 147, "parent": "3926951658001375", "t": 1451750420, "gender": "m", "verified": false, "verified_type": -1, "uid": "1466558125"}, {"original_text": " //@孔庆东:回复@阿郎的心声1966:好多二悲流氓都认同社会主义，他们不过是举着社会主义的旗子，企图掩盖自己不劳而获的龌龊心理。//@阿郎的心声1966:孔老师应该耐心点，这人虽笨，但好像也认同社会主义。//@孔庆东:回复@失忆-會過去的:你确实失忆了，因为不大愿意相信你也是二悲。", "username": "湾湾滴姥姥", "province": 63, "statuses_count": 54240, "friends_count": 666, "city": 1, "text": " ", "user_description": "", "mid": "3927001251068404", "verified_reason": "", "followers_count": 512, "parent": "3926951658001375", "t": 1451753520, "gender": "f", "verified": false, "verified_type": -1, "uid": "5459702281"}, {"original_text": "//@孔庆东:回复@阿郎的心声1966:好多二悲流氓都认同社会主义，他们不过是举着社会主义的旗子，企图掩盖自己不劳而获的龌龊心理。//@阿郎的心声1966:孔老师应该耐心点，这人虽笨，但好像也认同社会主义。//@孔庆东:回复@失忆-會過去的:你确实失忆了，因为不大愿意相信你也是二悲。", "username": "一塌糊涂V5", "province": 100, "statuses_count": 12399, "friends_count": 605, "city": 1000, "text": "", "user_description": "", "mid": "3927074987284701", "verified_reason": "", "followers_count": 163, "parent": "3926951658001375", "t": 1451771101, "gender": "m", "verified": false, "verified_type": -1, "uid": "2093659337"}, {"original_text": "//@孔庆东: 回复@阿郎的心声1966:好多二悲流氓都认同社会主义，他们不过是举着社会主义的旗子，企图掩盖自己不劳而获的龌龊心理。//@阿郎的心声1966:孔老师应该耐心点，这人虽笨，但好像也认同社会主义。//@孔庆东:回复@失忆-會過去的:你确实失忆了，因为不大愿意相信你也是二悲。", "username": "道士谷", "province": 37, "statuses_count": 29415, "friends_count": 155, "city": 6, "text": "", "user_description": "", "mid": "3927142574353995", "verified_reason": "", "followers_count": 133, "parent": "3926951658001375", "t": 1451787215, "gender": "f", "verified": false, "verified_type": -1, "uid": "2749052901"}, {"original_text": "//@孔庆东:回复@阿郎的心声1966:好多二悲流氓都认同社会主义，他们不过是举着社会主义的旗子，企图掩盖自己不劳而获的龌龊心理。//@阿郎的心声1966:孔老师应该耐心点，这人虽笨，但好像也认同社会主义。//@孔庆东:回复@失忆-會過去的:你确实失忆了，因为不大愿意相信你也是二悲。", "username": "单生权", "province": 33, "statuses_count": 2786, "friends_count": 47, "city": 2, "text": "", "user_description": "", "mid": "3932274024081283", "verified_reason": "", "followers_count": 52, "parent": "3926951658001375", "t": 1453010648, "gender": "m", "verified": false, "verified_type": -1, "uid": "2540425301"}]